index.py
serverinfo/__init__.py
serverinfo/info.py
serverinfo/si.py
src/__init__.py
src/index.py
serverinfo-0.2.10.dist-info/METADATA
serverinfo-0.2.10.dist-info/WHEEL
serverinfo-0.2.10.dist-info/top_level.txt
serverinfo-0.2.10.dist-info/RECORD
