Metadata-Version: 2.1
Name: serverinfo
Version: 0.2.10
Summary: AI Server(System + NVIDIA GPU) monitoring and power limit setting
Home-page: https://www.circul.us
Author: rippertnt
Author-email: rippertnt@circul.us
License: MIT
Requires-Python: >=3.6
Requires-Dist: psutil
Requires-Dist: xmltodict
